halon_api/__init__.py
halon_api/halon_api.py
halon_api-0.0.6.dist-info/LICENSE
halon_api-0.0.6.dist-info/METADATA
halon_api-0.0.6.dist-info/WHEEL
halon_api-0.0.6.dist-info/top_level.txt
halon_api-0.0.6.dist-info/RECORD
