Metadata-Version: 2.1
Name: halon-api
Version: 0.0.6
Summary: A wrapper for the REST API of mail transfer agent (MTA) Halon
Home-page: https://github.com/tobiasbp/halon-api
Author: Tobias Balle-Petersen
Author-email: tobiasbp@gmail.com
License: UNKNOWN
Platform: UNKNOWN
Classifier: Development Status :: 3 - Alpha
Classifier: License :: OSI Approved :: GNU Affero General Public License v3
Classifier: Programming Language :: Python :: 3 :: Only
Classifier: Programming Language :: Python :: 3
Classifier: Programming Language :: Python :: 3.6
Classifier: Programming Language :: Python :: 3.7
Classifier: Programming Language :: Python :: 3.8
Classifier: Programming Language :: Python :: 3.9
Classifier: Topic :: Communications :: Email :: Mail Transport Agents
Classifier: Operating System :: OS Independent
Requires-Python: >=3.6.1
License-File: LICENSE
Requires-Dist: requests
